tkinter_layout_helpers/__init__.py
tkinter_layout_helpers/grid_helper.py
tkinter_layout_helpers/pack_helper.py
tkinter_layout_helpers/parent_manager.py
tkinter_layout_helpers-0.6.0.dist-info/METADATA
tkinter_layout_helpers-0.6.0.dist-info/WHEEL
tkinter_layout_helpers-0.6.0.dist-info/licenses/LICENSE
tkinter_layout_helpers-0.6.0.dist-info/RECORD
