Metadata-Version: 2.4
Name: tkinter_layout_helpers
Version: 0.6.0
Summary: A library which is intended to simplify a placement of widgets with .grid() and .pack() methods
Project-URL: Homepage, https://github.com/insolor/tkinter-layout-helpers
Project-URL: Repository, https://github.com/insolor/tkinter-layout-helpers
Project-URL: Documentation, https://insolor.github.io/tkinter-layout-helpers
Author-email: insolor <insolor@gmail.com>
License-Expression: MIT
License-File: LICENSE
Keywords: grid,pack,tkinter
Classifier: Development Status :: 4 - Beta
Classifier: Intended Audience :: Developers
Classifier: License :: OSI Approved :: MIT License
Classifier: Operating System :: OS Independent
Classifier: Topic :: Software Development :: Libraries :: Python Modules
Requires-Python: >=3.9
Requires-Dist: typing-extensions
